lithio-1.0.3.dist-info/METADATA
lithio-1.0.3.dist-info/WHEEL
lithio-1.0.3.dist-info/entry_points.txt
lithio-1.0.3.dist-info/licenses/LICENSE
lithio/__init__.py
lithio/__main__.py
lithio/cli.py
lithio-1.0.3.dist-info/RECORD
