Metadata-Version: 2.1
Name: lithio
Version: 1.0.3
Summary: A Python-based clone of the GNU install command.
Keywords: install,GNU
Author-Email: voyager-2021 <voyager-2019@outlook.com>
License: MIT
Classifier: Development Status :: 5 - Production/Stable
Classifier: Intended Audience :: Developers
Classifier: License :: OSI Approved :: MIT License
Classifier: Programming Language :: Python :: 3
Classifier: Programming Language :: Python :: 3.10
Classifier: Programming Language :: Python :: 3.11
Classifier: Programming Language :: Python :: 3.12
Classifier: Programming Language :: Python :: 3.13
Project-URL: homepage, https://github.com/voyager-2021/lithio
Project-URL: repository, https://github.com/voyager-2021/lithio
Requires-Python: >=3.10
Requires-Dist: typer>=0.15.3
